example_test_package/__init__.py
example_test_package-1.0.0.dist-info/LICENSE
example_test_package-1.0.0.dist-info/METADATA
example_test_package-1.0.0.dist-info/WHEEL
example_test_package-1.0.0.dist-info/top_level.txt
example_test_package-1.0.0.dist-info/RECORD
