Metadata-Version: 2.1
Name: example-test-package
Version: 1.0.0
Summary: A example package with some pre-releases.
Home-page: https://github.com/BruceZhang1993
Author: Bruce Zhang
Author-email: zttt183525594@gmail.com
License: UNKNOWN
Platform: UNKNOWN
Classifier: Programming Language :: Python :: 3
Classifier: License :: OSI Approved :: MIT License
Classifier: Operating System :: OS Independent
